{
	"cards": [
		{ "id": "1", "text": "First task" },
		{ "id": "2", "text": "Second task" },
		{ "id": "3", "text": "Working on this" },
		{ "id": "4", "text": "Please check this" },
		{ "id": "5", "text": "Completed task" },
		{ "id": "6", "text": "Completed task" },
		{ "id": "7", "text": "Completed task" },
		{ "id": "8", "text": "Completed task" },
		{ "id": "9", "text": "Completed task" },
		{ "id": "10", "text": "Completed task" },
		{ "id": "11", "text": "Completed task" },
		{ "id": "12", "text": "Completed task" },
		{ "id": "13", "text": "Completed task" },
		{ "id": "14", "text": "Completed task" },
		{ "id": "15", "text": "Completed task" },
		{ "id": "16", "text": "Completed task" },
		{ "id": "17", "text": "Completed task" },
		{ "id": "18", "text": "Completed task" },
		{ "id": "19", "text": "Completed task" },
		{ "id": "20", "text": "Completed task" },
		{ "id": "21", "text": "Completed task" },
		{ "id": "22", "text": "Completed task" },
		{ "id": "23", "text": "Completed task" },
		{ "id": "24", "text": "Completed task" },
		{ "id": "25", "text": "Completed task" },
		{ "id": "26", "text": "Completed task" },
		{ "id": "27", "text": "Completed task" },
		{ "id": "28", "text": "Completed task" },
		{ "id": "29", "text": "Completed task" },
		{ "id": "30", "text": "Completed task" },
		{ "id": "31", "text": "Completed task" },
		{ "id": "32", "text": "Completed task" },
		{ "id": "33", "text": "Completed task" },
		{ "id": "34", "text": "Completed task" },
		{ "id": "35", "text": "Completed task" },
		{ "id": "36", "text": "Completed task" },
		{ "id": "37", "text": "Completed task" },
		{ "id": "38", "text": "Completed task" },
		{ "id": "39", "text": "Completed task" },
		{ "id": "40", "text": "Completed task" },
		{ "id": "41", "text": "Completed task" },
		{ "id": "42", "text": "Completed task" },
		{ "id": "43", "text": "Completed task" },
		{ "id": "44", "text": "Completed task" },
		{ "id": "45", "text": "Completed task" },
		{ "id": "46", "text": "Completed task" },
		{ "id": "47", "text": "Completed task" },
		{ "id": "48", "text": "Completed task" },
		{ "id": "49", "text": "Completed task" },
		{ "id": "50", "text": "Completed task" }
	]
}
